Metadata-Version: 1.0
Name: awsm-distributions
Version: 0.1
Summary: Gaussian and Binomial distributions
Home-page: UNKNOWN
Author: Paulo Alves
Author-email: UNKNOWN
License: UNKNOWN
Platform: UNKNOWN
